cloud/__init__.py
cloud/client.py
cloud/cloud_api.py
cloud/cloud_cli.py
cloud/model/__init__.py
cloud/model/entry.py
cloud/service/__init__.py
cloud/service/cloud.py
cloud/service/path_manipulation.py
simplecloud-0.0.0.5.dist-info/METADATA
simplecloud-0.0.0.5.dist-info/WHEEL
simplecloud-0.0.0.5.dist-info/entry_points.txt
simplecloud-0.0.0.5.dist-info/top_level.txt
simplecloud-0.0.0.5.dist-info/RECORD
